MANIFEST.in
README.md
requirements.txt
setup.py
molpdf/__init__.py
molpdf/molpdf.py
molpdf.egg-info/PKG-INFO
molpdf.egg-info/SOURCES.txt
molpdf.egg-info/dependency_links.txt
molpdf.egg-info/not-zip-safe
molpdf.egg-info/requires.txt
molpdf.egg-info/top_level.txt