Metadata-Version: 2.1
Name: molpdf
Version: 0.2.6
Summary: UNKNOWN
Home-page: https://www.github.com/Sulstice/molpdf
Author: Suliman Sharif
Author-email: sharifsuliman1@gmail.com
License: MPL 2.0
Keywords: pdf molecules smiles publication
Platform: UNKNOWN
Classifier: Development Status :: 4 - Beta
Classifier: Natural Language :: English
Classifier: License :: OSI Approved :: MIT License
Classifier: Intended Audience :: Developers
Classifier: Programming Language :: Python :: 3
Classifier: Programming Language :: Python :: 3.3
Classifier: Programming Language :: Python :: 3.4
Classifier: Programming Language :: Python :: 3.5
Classifier: Programming Language :: Python :: 3.6
Classifier: Programming Language :: Python :: 3.7
